django_join_unrelated/__init__.py
django_join_unrelated/compiler.py
django_join_unrelated/exception.py
django_join_unrelated/manager.py
django_join_unrelated/query.py
django_join_unrelated-0.2.0.dist-info/LICENSE
django_join_unrelated-0.2.0.dist-info/WHEEL
django_join_unrelated-0.2.0.dist-info/METADATA
django_join_unrelated-0.2.0.dist-info/RECORD
